WkSqlite3/WkSqlite3.py
WkSqlite3/__init__.py
WkSqlite3-1.0.1.dist-info/LICENSE
WkSqlite3-1.0.1.dist-info/METADATA
WkSqlite3-1.0.1.dist-info/WHEEL
WkSqlite3-1.0.1.dist-info/top_level.txt
WkSqlite3-1.0.1.dist-info/RECORD
