Metadata-Version: 2.1
Name: WkSqlite3
Version: 1.0.1
Summary: WkSqlite3 是一个用于简化 SQLite 数据库操作的 Python 封装类。它提供线程安全的连接管理及创建表、插入和查询数据等功能，帮助开发者高效地进行数据库操作。
Home-page: https://gitee.com/purify_wang/wk-sqlite3.git
Author: WANGKANG
Author-email: 1686617586@qq.com
License: GPL-2.0
Platform: all
Classifier: Intended Audience :: Developers
Classifier: Operating System :: OS Independent
Classifier: Natural Language :: Chinese (Simplified)
Classifier: Programming Language :: Python
Classifier: Programming Language :: Python :: 3
Classifier: Programming Language :: Python :: 3.10
Classifier: Programming Language :: Python :: 3.11
Classifier: Programming Language :: Python :: 3.12
Classifier: Topic :: Software Development :: Libraries
Requires-Python: >=3.10.0
License-File: LICENSE
Requires-Dist: WkLog
